pointcloudsimple/__init__.py
pointcloudsimple/engine.py
pointcloudsimple/gui.py
pointcloudsimple-0.0.2.dist-info/METADATA
pointcloudsimple-0.0.2.dist-info/WHEEL
pointcloudsimple-0.0.2.dist-info/top_level.txt
pointcloudsimple-0.0.2.dist-info/RECORD
